adbnx_adapter/__init__.py
adbnx_adapter/abc.py
adbnx_adapter/adapter.py
adbnx_adapter/controller.py
adbnx_adapter/typings.py
adbnx_adapter/utils.py
adbnx_adapter-5.0.5.dist-info/LICENSE
adbnx_adapter-5.0.5.dist-info/METADATA
adbnx_adapter-5.0.5.dist-info/WHEEL
adbnx_adapter-5.0.5.dist-info/top_level.txt
adbnx_adapter-5.0.5.dist-info/RECORD
