Metadata-Version: 2.1
Name: adbnx_adapter
Version: 5.0.5
Summary: Convert ArangoDB graphs to NetworkX & vice-versa.
Author-email: Anthony Mahanna <anthony.mahanna@arangodb.com>
License: Apache License
Project-URL: Homepage, https://github.com/arangoml/networkx-adapter
Keywords: arangodb,networkx,adapter
Classifier: Intended Audience :: Developers
Classifier: License :: OSI Approved :: Apache Software License
Classifier: Operating System :: OS Independent
Classifier: Programming Language :: Python :: 3
Classifier: Programming Language :: Python :: 3.8
Classifier: Programming Language :: Python :: 3.9
Classifier: Programming Language :: Python :: 3.10
Classifier: Programming Language :: Python :: 3.11
Classifier: Programming Language :: Python :: 3.12
Classifier: Topic :: Utilities
Classifier: Typing :: Typed
Requires-Python: >=3.8
License-File: LICENSE
Requires-Dist: requests>=2.27.1
Requires-Dist: python-arango>=7.4
Requires-Dist: networkx>=2.5.1
Requires-Dist: rich>=12.5.1
Requires-Dist: setuptools>=45
Provides-Extra: dev
Requires-Dist: black==23.3.0; extra == "dev"
Requires-Dist: flake8==6.0.0; extra == "dev"
Requires-Dist: Flake8-pyproject; extra == "dev"
Requires-Dist: isort==5.12.0; extra == "dev"
Requires-Dist: mypy==1.4.1; extra == "dev"
Requires-Dist: pytest>=6.0.0; extra == "dev"
Requires-Dist: pytest-cov>=2.0.0; extra == "dev"
Requires-Dist: coveralls>=3.3.1; extra == "dev"
Requires-Dist: types-setuptools; extra == "dev"
